{"zip": "45262-5737",
  "sector": "Industrials",
  "fullTimeEmployees": 43000,
  "longBusinessSummary": "Cintas Corporation provides corporate identity uniforms and related business services primarily in the United States, Canada, and Latin America. It operates through Uniform Rental and Facility Services, First Aid and Safety Services, and All Other segments. The company rents and services uniforms and other garments, including flame resistant clothing, mats, mops and shop towels, and other ancillary items; and provides restroom cleaning services and supplies, as well as sells uniforms. It also offers first aid and safety services, and fire protection products and services. The company provides its products and services through its distribution network and local delivery routes, or local representatives to small service and manufacturing companies, as well as major corporations. Cintas Corporation was founded in 1968 and is headquartered in Cincinnati, Ohio.",
  "city": "Cincinnati",
  "phone": "513 459 1200",
  "state": "OH",
  "country": "United States",
  "companyOfficers": [],
  "website": "https://www.cintas.com",
  "maxAge": 1,
  "address1": "6800 Cintas Boulevard",
  "industry": "Specialty Business Services",
  "address2": "PO Box 625737",
  "ebitdaMargins": 0.23686,
  "profitMargins": 0.15464,
  "grossMargins": 0.46253,
  "operatingCashflow": 1573639936,
  "revenueGrowth": 0.142,
  "operatingMargins": 0.20106001,
  "ebitda": 1924286976,
  "targetLowPrice": 373,
  "recommendationKey": "buy",
  "grossProfits": 3632246000,
  "freeCashflow": 1112018432,
  "targetMedianPrice": 450,
  "currentPrice": 410.94,
  "earningsGrowth": 0.09,
  "currentRatio": 1.718,
  "returnOnAssets": 0.12667,
  "numberOfAnalystOpinions": 11,
  "targetMeanPrice": 443.55,
  "debtToEquity": 98.142,
  "returnOnEquity": 0.38425,
  "targetHighPrice": 495,
  "totalCash": 74558000,
  "totalDebt": 3169617920,
  "totalRevenue": 8123962880,
  "totalCashPerShare": 0.734,
  "financialCurrency": "USD",
  "revenuePerShare": 79.1,
  "quickRatio": 0.724,
  "recommendationMean": 2.3,
  "exchange": "NMS",
  "shortName": "Cintas Corporation",
  "longName": "Cintas Corporation",
  "exchangeTimezoneName": "America/New_York",
  "exchangeTimezoneShortName": "EDT",
  "isEsgPopulated": "False",
  "gmtOffSetMilliseconds": "-14400000",
  "quoteType": "EQUITY",
  "symbol": "CTAS",
  "messageBoardId": "finmb_260725",
  "market": "us_market",
  "annualHoldingsTurnover": "None",
  "enterpriseToRevenue": 5.734,
  "beta3Year": "None",
  "enterpriseToEbitda": 24.208,
  "52WeekChange": -0.056242764,
  "morningStarRiskRating": "None",
  "forwardEps": 13.92,
  "revenueQuarterlyGrowth": "None",
  "sharesOutstanding": 101545000,
  "fundInceptionDate": "None",
  "annualReportExpenseRatio": "None",
  "totalAssets": "None",
  "bookValue": 31.809,
  "sharesShort": 1135771,
  "sharesPercentSharesOut": 0.0112,
  "fundFamily": "None",
  "lastFiscalYearEnd": 1653955200,
  "heldPercentInstitutions": 0.6497,
  "netIncomeToCommon": 1250380032,
  "trailingEps": 11.93,
  "lastDividendValue": 1.15,
  "SandP52WeekChange": -0.19665772,
  "priceToBook": 12.918985,
  "heldPercentInsiders": 0.1505,
  "nextFiscalYearEnd": 1717113600,
  "yield": "None",
  "mostRecentQuarter": 1661904000,
  "shortRatio": 2.26,
  "sharesShortPreviousMonthDate": 1663200000,
  "floatShares": 86246505,
  "beta": 1.380619,
  "enterpriseValue": 46583873536,
  "priceHint": 2,
  "threeYearAverageReturn": "None",
  "lastSplitDate": 952473600,
  "lastSplitFactor": "3:2",
  "legalType": "None",
  "lastDividendDate": 1660262400,
  "morningStarOverallRating": "None",
  "earningsQuarterlyGrowth": 0.062,
  "priceToSalesTrailing12Months": 5.1365204,
  "dateShortInterest": 1665705600,
  "pegRatio": 3.02,
  "ytdReturn": "None",
  "forwardPE": 29.521551,
  "lastCapGain": "None",
  "shortPercentOfFloat": 0.013200001,
  "sharesShortPriorMonth": 1205745,
  "impliedSharesOutstanding": 0,
  "category": "None",
  "fiveYearAverageReturn": "None",
  "previousClose": 415.81,
  "regularMarketOpen": 411.72,
  "twoHundredDayAverage": 396.4343,
  "trailingAnnualDividendYield": 0.009619778,
  "payoutRatio": 0.3353,
  "volume24Hr": "None",
  "regularMarketDayHigh": 418.88,
  "navPrice": "None",
  "averageDailyVolume10Day": 382790,
  "regularMarketPreviousClose": 415.81,
  "fiftyDayAverage": 406.5362,
  "trailingAnnualDividendRate": 4,
  "open": 411.72,
  "toCurrency": "None",
  "averageVolume10days": 382790,
  "expireDate": "None",
  "algorithm": "None",
  "dividendRate": 4.2,
  "exDividendDate": 1668384000,
  "circulatingSupply": "None",
  "startDate": "None",
  "regularMarketDayLow": 410.19,
  "currency": "USD",
  "trailingPE": 34.445934,
  "regularMarketVolume": 425714,
  "lastMarket": "None",
  "maxSupply": "None",
  "openInterest": "None",
  "marketCap": 41728901120,
  "volumeAllCurrencies": "None",
  "strikePrice": "None",
  "averageVolume": 415962,
  "dayLow": 410.19,
  "ask": 411.72,
  "askSize": 800,
  "volume": 425714,
  "fiftyTwoWeekHigh": 461.44,
  "fromCurrency": "None",
  "fiveYearAvgDividendYield": 1,
  "fiftyTwoWeekLow": 343.86,
  "bid": 394,
  "tradeable": "False",
  "dividendYield": 0.0098,
  "bidSize": 1800,
  "dayHigh": 418.88,
  "coinMarketCapLink": "None",
  "regularMarketPrice": 410.94,
  "preMarketPrice": 427.87,
  "logo_url": "https://logo.clearbit.com/cintas.com"
}
